<?xml version="1.0" encoding="utf-8" ?><dwsync><file name="instagram.png" server="ftp.jartstuff.com" local="3689788759" remote="3690212040" Dst="-1" /><file name="Travelor.jpg" server="ftp.jartstuff.com" local="3687894596" remote="3690212040" Dst="-1" /><file name="Meditator.jpg" server="ftp.jartstuff.com" local="3687894834" remote="3690212040" Dst="-1" /><file name="AdventurerTime.jpg" server="ftp.jartstuff.com" local="3687894361" remote="3690212040" Dst="-1" /><file name="marek-okon-WScpndZFrOM-unsplash.jpg" server="ftp.jartstuff.com" local="3687895854" remote="3690212040" Dst="-1" /><file name="gettyimages-1271720342-2048x2048.jpg" server="ftp.jartstuff.com" local="3687891638" remote="3690212040" Dst="-1" /><file name="Swimmer.jpg" server="ftp.jartstuff.com" local="3687894738" remote="3690212040" Dst="-1" /><file name="CityKid.jpg" server="ftp.jartstuff.com" local="3687894533" remote="3690212100" Dst="-1" /><file name="hawaii-from-space-988x768.jpg" server="ftp.jartstuff.com" local="3690171052" remote="3690212100" Dst="-1" /><file name="external-content.duckduckgo.gif" server="ftp.jartstuff.com" local="3689794662" remote="3690212100" Dst="-1" /><file name="facebook.png" server="ftp.jartstuff.com" local="3689788605" remote="3690212100" Dst="-1" /><file name="Snapchat.png" server="ftp.jartstuff.com" local="3689788848" remote="3690212100" Dst="-1" /><file name="Culture.jpg" server="ftp.jartstuff.com" local="3687895414" remote="3690212100" Dst="-1" /></dwsync>